month_range/HalfYear.py
month_range/Month.py
month_range/MonthRange.py
month_range/QuarterYear.py
month_range/Year.py
month_range/__init__.py
month_range/parse_util.py
month_range/util.py
month_range-0.0.6.dist-info/licenses/LICENCE
month_range-0.0.6.dist-info/METADATA
month_range-0.0.6.dist-info/WHEEL
month_range-0.0.6.dist-info/top_level.txt
month_range-0.0.6.dist-info/RECORD
