Metadata-Version: 2.4
Name: month-range
Version: 0.0.6
Summary: Handling of month based time ranges.
Author-email: Felix Hofmann <felix@hofmann.rocks>
Keywords: date,month,range,calendar,period,finance,quarter,fiscal
Classifier: Development Status :: 3 - Alpha
Classifier: Intended Audience :: Developers
Classifier: License :: OSI Approved :: MIT License
Classifier: Programming Language :: Python :: 3
Classifier: Programming Language :: Python :: 3.8
Classifier: Programming Language :: Python :: 3.9
Classifier: Programming Language :: Python :: 3.10
Classifier: Programming Language :: Python :: 3.11
Classifier: Programming Language :: Python :: 3.12
Classifier: Programming Language :: Python :: 3.13
Classifier: Topic :: Software Development :: Libraries :: Python Modules
Classifier: Topic :: Office/Business :: Financial
Classifier: Topic :: Utilities
Requires-Python: >=3.13
License-File: LICENCE
Dynamic: license-file
